asyncwinrm/__init__.py
asyncwinrm/encryption.py
asyncwinrm/exceptions.py
asyncwinrm/protocol.py
asyncwinrm/transport.py
asyncwinrm/vendor/__init__.py
asyncwinrm-0.4.dist-info/DESCRIPTION.rst
asyncwinrm-0.4.dist-info/METADATA
asyncwinrm-0.4.dist-info/RECORD
asyncwinrm-0.4.dist-info/WHEEL
asyncwinrm-0.4.dist-info/metadata.json
asyncwinrm-0.4.dist-info/top_level.txt
